utils2p/__init__.py
utils2p/main.py
utils2p/synchronization.py
utils2p/external/__init__.py
utils2p/external/tifffile/__init__.py
utils2p/external/tifffile/_tifffile.cpython-312-darwin.so
utils2p/external/tifffile/tifffile.py
utils2p-1.0.1.dist-info/LICENSE
utils2p-1.0.1.dist-info/METADATA
utils2p-1.0.1.dist-info/WHEEL
utils2p-1.0.1.dist-info/top_level.txt
utils2p-1.0.1.dist-info/RECORD
