Metadata-Version: 2.1
Name: utils2p
Version: 1.0.1
Summary: Basic utility functions for 2 photon image data generated using ThorImage and ThorSync.
Home-page: https://github.com/NeLy-EPFL/utils2p
Author: Florian Aymanns
Author-email: florian.aymanns@epfl.ch
License-File: LICENSE
Requires-Dist: numpy
Requires-Dist: pytest
Requires-Dist: scipy
Requires-Dist: h5py
